cubituskinematics/Bezier.py
cubituskinematics/Core.py
cubituskinematics/Kinematics.py
cubituskinematics/Mathematics.py
cubituskinematics/__init__.py
cubituskinematics/cubitus.xml
cubituskinematics-0.1.0.dist-info/LICENSE.txt
cubituskinematics-0.1.0.dist-info/METADATA
cubituskinematics-0.1.0.dist-info/WHEEL
cubituskinematics-0.1.0.dist-info/top_level.txt
cubituskinematics-0.1.0.dist-info/RECORD
