Metadata-Version: 2.1
Name: cubituskinematics
Version: 0.1.0
Summary: Controller library for C.U.B.I.T.U.S. Robotic Arm
Home-page: https://pypi.org/project/cubituskinematics/
Author: Oliver Kudzia
Author-email: olinox11@gmail.com
License: MIT
Keywords: cubitus,robotic arm,inverse kinematics,forward kinematics,tuke,kkui
Platform: UNKNOWN
Classifier: Development Status :: 5 - Production/Stable
Classifier: Intended Audience :: Education
Classifier: Operating System :: Microsoft :: Windows :: Windows 10
Classifier: Operating System :: Unix
Classifier: Programming Language :: Python :: 3
Classifier: Programming Language :: Python :: 3.7
Classifier: License :: OSI Approved :: MIT License
Requires-Python: >=3.7
Requires-Dist: numpy
Requires-Dist: matplotlib (>=3.3.3)
Requires-Dist: pyserial
